[
    {
        "question": "How often should I replace my contact lenses?",
        "answer": "Daily disposables should be replaced every day; bi‑weekly lenses every two weeks; monthly lenses every month."
    },
    {
        "question": "Can I sleep in my lenses?",
        "answer": "Unless specified as extended‑wear, remove lenses before sleeping to avoid infection risk."
    },
    {
        "question": "How do I clean my contact lenses?",
        "answer": "Use a recommended lens solution, rub and rinse lenses, and store them in fresh solution."
    },
    {
        "question": "Can I wear makeup with contact lenses?",
        "answer": "Yes, but apply makeup after inserting lenses and avoid oil-based products."
    },
    {
        "question": "What should I do if my lenses feel uncomfortable?",
        "answer": "Remove them immediately, rinse with solution, and consult your eye care professional if discomfort persists."
    },
    {
        "question": "Can I swim with contact lenses?",
        "answer": "It's best to remove them before swimming to prevent irritation or infection."
    },
    {
        "question": "How do I know if my lenses are expired?",
        "answer": "Check the expiration date on the packaging; do not use expired lenses."
    },
    {
        "question": "Can I wear contact lenses if I have dry eyes?",
        "answer": "Yes, but consult your eye care professional for suitable options."
    },
    {
        "question": "What should I do if I lose a lens?",
        "answer": "If you can't find it, remove the other lens and consult your eye care professional."
    }
]